src/__init__.py
src/cli.py
src/reviewer.py
src/lib/__init__.py
src/lib/github_pr.py
src/lib/openai_assistant.py
condor_code_reviewer-1.3.5.dist-info/METADATA
condor_code_reviewer-1.3.5.dist-info/WHEEL
condor_code_reviewer-1.3.5.dist-info/entry_points.txt
condor_code_reviewer-1.3.5.dist-info/top_level.txt
condor_code_reviewer-1.3.5.dist-info/RECORD
