Metadata-Version: 2.1
Name: condor_code_reviewer
Version: 1.3.5
Requires-Dist: openai
Requires-Dist: PyGithub
